Workbook
Name aporte: APP!$D$15
Name patrimonio: APP!$D$18
Name qtd_anos: APP!$D$16
Name rendimento_carteira: APP!$D$11
Name salario: APP!$D$10
Name sugestao_investimento: APP!$D$12
Name taxa_mensal: APP!$D$17

Sheet APP
B9: CONFIGURAÇÕES
B10: Salário | D10: 2000
B11: Rendimento carteira | D11: 0.006
B12: Sugestão de Investimento (30%) | D12: =D10*30% -> 600
B14: INVESTIMENTO MENSAL
B15: Quanto investir por mês? | D15: 200
B16: Por quantos anos? | D16: 5
B17: Taxa de rendimento mensal? | D17: 0.01079
B18: Patrimônio acumulado? | D18: =FV(taxa_mensal,qtd_anos*12,aporte*-1) -> 16755.383
B19: Dividendos mensais? | D19: =patrimonio*rendimento_carteira -> 100.5323
B21: CENÁRIOS | D21: Dividendo
A22: 2 | B22: Quanto em 2 anos? | C22: =FV($D$17,$A22*12,$D$15*-1) -> 5445.5255 | D22: =C22*rendimento_carteira -> 32.673153
A23: 5 | B23: Quanto em 5 anos? | C23: =FV($D$17,$A23*12,$D$15*-1) -> 16755.383 | D23: =C23*rendimento_carteira -> 100.5323
A24: 10 | B24: Quanto em 10 anos? | C24: =FV($D$17,$A24*12,$D$15*-1) -> 48656.843 | D24: =C24*rendimento_carteira -> 291.94106
A25: 20 | B25: Quanto em 20 anos? | C25: =FV($D$17,$A25*12,$D$15*-1) -> 225039.68 | D25: =C25*rendimento_carteira -> 1350.2381
A26: 30 | B26: Quanto em 30 anos? | C26: =FV($D$17,$A26*12,$D$15*-1) -> 864433.93 | D26: =C26*rendimento_carteira -> 5186.6036
B29: PERFIL | C29: Moderado
B30: VALOR A SER INVESTIDO POR MÊS | C30: =aporte -> 200
B32: TIPO DE FII | C32: Percentual Sugerido | D32: Valores
B33: PAPEL | C33: =VLOOKUP($C$29&"-"&B33,'Base PROCV'!$A:$D,4,FALSE) -> 0.32 | D33: =C33*$C$30 -> 64
B34: TIJOLOS | C34: =VLOOKUP($C$29&"-"&B34,'Base PROCV'!$A:$D,4,FALSE) -> 0.35 | D34: =C34*$C$30 -> 70
B35: HÍBRIDOS | C35: =VLOOKUP($C$29&"-"&B35,'Base PROCV'!$A:$D,4,FALSE) -> 0.08 | D35: =C35*$C$30 -> 16
B36: FOFs | C36: =VLOOKUP($C$29&"-"&B36,'Base PROCV'!$A:$D,4,FALSE) -> 0.05 | D36: =C36*$C$30 -> 10
B37: DESENVOLVIMENTO | C37: =VLOOKUP($C$29&"-"&B37,'Base PROCV'!$A:$D,4,FALSE) -> 0.1 | D37: =C37*$C$30 -> 20
B38: HOTELARIAS | C38: =VLOOKUP($C$29&"-"&B38,'Base PROCV'!$A:$D,4,FALSE) -> 0.1 | D38: =C38*$C$30 -> 20
D39: =SUM(D33:D38) -> 200

Sheet Base PROCV
G1: %
A2: CHAVE | B2: PERFIL | C2: TIPO DE FII | D2: % | F2: Moderado-TIJOLOS | G2: =VLOOKUP(F2,$A:$D,4,FALSE) -> 0.35
A3: =B3&"-"&C3 -> Conservador-PAPEL | B3: Conservador | C3: PAPEL | D3: 0.3
A4: =B4&"-"&C4 -> Conservador-TIJOLOS | B4: Conservador | C4: TIJOLOS | D4: 0.5
A5: =B5&"-"&C5 -> Conservador-HÍBRIDOS | B5: Conservador | C5: HÍBRIDOS | D5: 0.1
A6: =B6&"-"&C6 -> Conservador-FOFs | B6: Conservador | C6: FOFs | D6: 0.1
A7: =B7&"-"&C7 -> Conservador-DESENVOLVIMENTO | B7: Conservador | C7: DESENVOLVIMENTO | D7: 0
A8: =B8&"-"&C8 -> Conservador-HOTELARIAS | B8: Conservador | C8: HOTELARIAS | D8: 0
A9: =B9&"-"&C9 -> Moderado-PAPEL | B9: Moderado | C9: PAPEL | D9: 0.32
A10: =B10&"-"&C10 -> Moderado-TIJOLOS | B10: Moderado | C10: TIJOLOS | D10: 0.35
A11: =B11&"-"&C11 -> Moderado-HÍBRIDOS | B11: Moderado | C11: HÍBRIDOS | D11: 0.08
A12: =B12&"-"&C12 -> Moderado-FOFs | B12: Moderado | C12: FOFs | D12: 0.05
A13: =B13&"-"&C13 -> Moderado-DESENVOLVIMENTO | B13: Moderado | C13: DESENVOLVIMENTO | D13: 0.1
A14: =B14&"-"&C14 -> Moderado-HOTELARIAS | B14: Moderado | C14: HOTELARIAS | D14: 0.1
... A20: =B20&"-"&C20 -> Agressivo-HOTELARIAS | B20: Agressivo | C20: HOTELARIAS | D20: 0.1
